machiavelli/__init__.py
machiavelli/__main__.py
machiavelli/command.py
machiavelli/solver.py
machiavelli-0.1.0.dist-info/LICENSE.txt
machiavelli-0.1.0.dist-info/METADATA
machiavelli-0.1.0.dist-info/WHEEL
machiavelli-0.1.0.dist-info/entry_points.txt
machiavelli-0.1.0.dist-info/top_level.txt
machiavelli-0.1.0.dist-info/RECORD
