Metadata-Version: 2.1
Name: machiavelli
Version: 0.1.0
Summary: Solver for the card game Machiavelli
Home-page: https://github.com/cduck/machiavelli
Author: Casey Duckering
License: UNKNOWN
Download-URL: https://github.com/cduck/machiavelli/archive/0.1.0.tar.gz
Keywords: card game,game,CSP
Platform: UNKNOWN
Classifier: License :: OSI Approved :: MIT License
Classifier: Development Status :: 3 - Alpha
Classifier: Programming Language :: Python :: 3
Classifier: Programming Language :: Python :: 3.7
Classifier: Programming Language :: Python :: 3.8
Classifier: Programming Language :: Python :: 3.9
License-File: LICENSE.txt
Requires-Dist: numpy (~=1.11)
Requires-Dist: cvxpy (~=1.1)
Requires-Dist: cvxopt (~=1.2)
Requires-Dist: termcolor (~=1.1)
Requires-Dist: colorama (~=0.3)
